rosmetasys/__init__.py
rosmetasys/cli.py
rosmetasys/console.py
rosmetasys/export.py
rosmetasys/requirements.txt
rosmetasys-1.0.2.dist-info/METADATA
rosmetasys-1.0.2.dist-info/WHEEL
rosmetasys-1.0.2.dist-info/entry_points.txt
rosmetasys-1.0.2.dist-info/licenses/LICENSE
rosmetasys-1.0.2.dist-info/RECORD
