Metadata-Version: 2.3
Name: rosmetasys
Version: 1.0.2
Summary: Commandline tool to export the meta information of a ROS package.
Project-URL: Homepage, https://github.com/vschroeter/rosmetasys
Project-URL: Issues, https://github.com/vschroeter/rosmetasys/issues
Author-email: Valentin Schröter <valentin.schroeter@student.hpi.uni-potsdam.de>
License-File: LICENSE
Classifier: License :: OSI Approved :: MIT License
Classifier: Operating System :: OS Independent
Classifier: Programming Language :: Python :: 3
Requires-Python: >=3.8
Requires-Dist: click
Requires-Dist: click-aliases
Requires-Dist: inquirerpy
Requires-Dist: rich
